SummarizeIt/__init__.py
SummarizeIt/bot.py
SummarizeIt-0.0.2.dist-info/METADATA
SummarizeIt-0.0.2.dist-info/WHEEL
SummarizeIt-0.0.2.dist-info/top_level.txt
SummarizeIt-0.0.2.dist-info/RECORD
