Metadata-Version: 2.1
Name: SummarizeIt
Version: 0.0.2
Summary: Package for analyzing Youtube Videos from searching by relevant entities to analyzing sentiments and clustering different parts of the video according to your liking 
Home-page: https://github.com/Jash271/YouGlance
Author: Jash Shah
Author-email: shahjash271@gmail.com
License: MIT
Platform: UNKNOWN
Classifier: Development Status :: 4 - Beta
Classifier: License :: OSI Approved :: MIT License
Classifier: Programming Language :: Python
Classifier: Topic :: Software Development :: Libraries
Classifier: Topic :: Software Development :: Libraries :: Python Modules
Classifier: Intended Audience :: Developers
Requires-Python: >=3.6.8
Requires-Dist: nltk
